[
    {
        "function": "new_block",
        "options": "minecraft:stone_button"
    },
    {
        "function": "map_properties",
        "options": {
            "material": {
                "\"stone\"": [
                    {
                        "function": "new_block",
                        "options": "minecraft:stone_button"
                    }
                ],
                "\"oak\"": [
                    {
                        "function": "new_block",
                        "options": "minecraft:wooden_button"
                    }
                ],
                "\"acacia\"": [
                    {
                        "function": "new_block",
                        "options": "minecraft:acacia_button"
                    }
                ],
                "\"birch\"": [
                    {
                        "function": "new_block",
                        "options": "minecraft:birch_button"
                    }
                ],
                "\"dark_oak\"": [
                    {
                        "function": "new_block",
                        "options": "minecraft:dark_oak_button"
                    }
                ],
                "\"jungle\"": [
                    {
                        "function": "new_block",
                        "options": "minecraft:jungle_button"
                    }
                ],
                "\"spruce\"": [
                    {
                        "function": "new_block",
                        "options": "minecraft:spruce_button"
                    }
                ]
            },
            "powered": {
                "\"false\"": [
                    {
                        "function": "map_properties",
                        "options": {
                            "face": {
                                "\"ceiling\"": [
                                    {
                                        "function": "new_properties",
                                        "options": {
                                            "block_data": "0"
                                        }
                                    }
                                ],
                                "\"floor\"": [
                                    {
                                        "function": "new_properties",
                                        "options": {
                                            "block_data": "1"
                                        }
                                    }
                                ],
                                "\"wall\"": [
                                    {
                                        "function": "map_properties",
                                        "options": {
                                            "facing": {
                                                "\"north\"": [
                                                    {
                                                        "function": "new_properties",
                                                        "options": {
                                                            "block_data": "2"
                                                        }
                                                    }
                                                ],
                                                "\"south\"": [
                                                    {
                                                        "function": "new_properties",
                                                        "options": {
                                                            "block_data": "3"
                                                        }
                                                    }
                                                ],
                                                "\"west\"": [
                                                    {
                                                        "function": "new_properties",
                                                        "options": {
                                                            "block_data": "4"
                                                        }
                                                    }
                                                ],
                                                "\"east\"": [
                                                    {
                                                        "function": "new_properties",
                                                        "options": {
                                                            "block_data": "5"
                                                        }
                                                    }
                                                ]
                                            }
                                        }
                                    }
                                ]
                            }
                        }
                    }
                ],
                "\"true\"": [
                    {
                        "function": "map_properties",
                        "options": {
                            "face": {
                                "\"ceiling\"": [
                                    {
                                        "function": "new_properties",
                                        "options": {
                                            "block_data": "8"
                                        }
                                    }
                                ],
                                "\"floor\"": [
                                    {
                                        "function": "new_properties",
                                        "options": {
                                            "block_data": "9"
                                        }
                                    }
                                ],
                                "\"wall\"": [
                                    {
                                        "function": "map_properties",
                                        "options": {
                                            "facing": {
                                                "\"north\"": [
                                                    {
                                                        "function": "new_properties",
                                                        "options": {
                                                            "block_data": "10"
                                                        }
                                                    }
                                                ],
                                                "\"south\"": [
                                                    {
                                                        "function": "new_properties",
                                                        "options": {
                                                            "block_data": "11"
                                                        }
                                                    }
                                                ],
                                                "\"west\"": [
                                                    {
                                                        "function": "new_properties",
                                                        "options": {
                                                            "block_data": "12"
                                                        }
                                                    }
                                                ],
                                                "\"east\"": [
                                                    {
                                                        "function": "new_properties",
                                                        "options": {
                                                            "block_data": "13"
                                                        }
                                                    }
                                                ]
                                            }
                                        }
                                    }
                                ]
                            }
                        }
                    }
                ]
            }
        }
    }
]