[
    {
        "function": "map_properties",
        "options": {
            "variant": {
                "\"quartz_block\"": [
                    {
                        "function": "new_block",
                        "options": "universal_minecraft:quartz_block"
                    }
                ],
                "\"chiseled_quartz_block\"": [
                    {
                        "function": "new_block",
                        "options": "universal_minecraft:chiseled_quartz_block"
                    }
                ],
                "\"quartz_pillar_y\"": [
                    {
                        "function": "new_block",
                        "options": "universal_minecraft:quartz_pillar"
                    },
                    {
                        "function": "new_properties",
                        "options": {
                            "axis": "\"y\""
                        }
                    }
                ],
                "\"quartz_pillar_x\"": [
                    {
                        "function": "new_block",
                        "options": "universal_minecraft:quartz_pillar"
                    },
                    {
                        "function": "new_properties",
                        "options": {
                            "axis": "\"x\""
                        }
                    }
                ],
                "\"quartz_pillar_z\"": [
                    {
                        "function": "new_block",
                        "options": "universal_minecraft:quartz_pillar"
                    },
                    {
                        "function": "new_properties",
                        "options": {
                            "axis": "\"z\""
                        }
                    }
                ]
            }
        }
    }
]