[
    {
        "function": "walk_input_nbt",
        "options": {
            "type": "compound",
            "keys": {
                "utags": {
                    "type": "compound",
                    "nested_default": [],
                    "self_default": [],
                    "keys": {
                        "Text1": {
                            "type": "string",
                            "functions": [
                                {
                                    "function": "carry_nbt",
                                    "options": {
                                        "path": []
                                    }
                                }
                            ]
                        },
                        "Text2": {
                            "type": "string",
                            "functions": [
                                {
                                    "function": "carry_nbt",
                                    "options": {
                                        "path": []
                                    }
                                }
                            ]
                        },
                        "Text3": {
                            "type": "string",
                            "functions": [
                                {
                                    "function": "carry_nbt",
                                    "options": {
                                        "path": []
                                    }
                                }
                            ]
                        },
                        "Text4": {
                            "type": "string",
                            "functions": [
                                {
                                    "function": "carry_nbt",
                                    "options": {
                                        "path": []
                                    }
                                }
                            ]
                        },
                        "keepPacked": {
                            "type": "byte",
                            "functions": [
                                {
                                    "function": "carry_nbt",
                                    "options": {
                                        "path": []
                                    }
                                }
                            ]
                        }
                    }
                }
            }
        }
    },
    {
        "function": "walk_input_nbt",
        "options": {
            "type": "compound",
            "keys": {
                "utags": {
                    "type": "compound"
                }
            },
            "self_default": [
                {
                    "function": "carry_nbt",
                    "options": {}
                }
            ],
            "nested_default": [
                {
                    "function": "carry_nbt",
                    "options": {}
                }
            ]
        }
    },
    {
        "function": "new_block",
        "options": "minecraft:wall_sign"
    },
    {
        "function": "map_properties",
        "options": {
            "material": {
                "\"oak\"": [
                    {
                        "function": "new_block",
                        "options": "minecraft:wall_sign"
                    }
                ]
            }
        }
    },
    {
        "function": "carry_properties",
        "options": {
            "facing": [
                "\"north\"",
                "\"south\"",
                "\"west\"",
                "\"east\""
            ]
        }
    }
]