[
    {
        "function": "new_block",
        "options": "minecraft:furnace"
    },
    {
        "function": "map_properties",
        "options": {
            "lit": {
                "\"false\"": [
                    {
                        "function": "new_block",
                        "options": "minecraft:furnace"
                    }
                ],
                "\"true\"": [
                    {
                        "function": "new_block",
                        "options": "minecraft:lit_furnace"
                    }
                ]
            },
            "facing": {
                "\"north\"": [
                    {
                        "function": "new_properties",
                        "options": {
                            "minecraft:cardinal_direction": "\"north\""
                        }
                    }
                ],
                "\"south\"": [
                    {
                        "function": "new_properties",
                        "options": {
                            "minecraft:cardinal_direction": "\"south\""
                        }
                    }
                ],
                "\"west\"": [
                    {
                        "function": "new_properties",
                        "options": {
                            "minecraft:cardinal_direction": "\"west\""
                        }
                    }
                ],
                "\"east\"": [
                    {
                        "function": "new_properties",
                        "options": {
                            "minecraft:cardinal_direction": "\"east\""
                        }
                    }
                ]
            }
        }
    }
]