{
    "properties": {
        "conditional": [
            "false",
            "true"
        ],
        "facing": [
            "north",
            "east",
            "south",
            "west",
            "up",
            "down"
        ],
        "mode": [
            "impulse",
            "chain",
            "repeating"
        ]
    },
    "defaults": {
        "conditional": "false",
        "facing": "north",
        "mode": "impulse"
    },
    "nbt_identifier": [
        "universal_minecraft",
        "command_block"
    ],
    "snbt": "{utags: {isMovable: 1b,auto: 0b,Command: \"\",conditionMet: 0b,CustomName: \"{\\\"text\\\":\\\"@\\\"}\",ExecuteOnFirstTick: 0b,LPCommandMode: 0,LPCondionalMode: 0b,LPRedstoneMode: 0b,LastExecution: 0l,LastOutput: \"\",LastOutputParams: [],powered: 0b,SuccessCount: 0,TickDelay: 0,TrackOutput: 1b,Version: 10,UpdateLastExecution: 1b}}"
}